<?xml version="1.0" encoding="UTF-8" standalone="yes"?>
<persons>
    <person id="4">
        <name>Illya</name>
        <lastName>Pinchuk</lastName>
        <age>20</age>
        <post>QA</post>
    </person>
    <person id="6">
        <name>Vladimir</name>
        <lastName>Kudyna</lastName>
        <age>35</age>
        <post>QA</post>
    </person>
    <person id="8">
        <name>Violete</name>
        <lastName>Egorova</lastName>
        <age>40</age>
        <post>DIRECTOR</post>
    </person>
    <person id="9">
        <name>Svyatoslav</name>
        <lastName>Drobich</lastName>
        <age>45</age>
        <post>DIRECTOR</post>
    </person>
    <person id="2">
        <name>Anton</name>
        <lastName>Zemlyankin</lastName>
        <age>22</age>
        <post>DEVELOPER</post>
    </person>
    <person id="5">
        <name>Elena</name>
        <lastName>Kirichenko</lastName>
        <age>30</age>
        <post>QA</post>
    </person>
</persons>
